firebase_auth/__init__.py
firebase_auth/firebase_auth.py
sseclient/__init__.py
sseclient/sseclient.py
firebase_auth-3.0.28.dist-info/METADATA
firebase_auth-3.0.28.dist-info/WHEEL
firebase_auth-3.0.28.dist-info/top_level.txt
firebase_auth-3.0.28.dist-info/RECORD
